clitify/__init__.py
clitify/main.py
clitify/spcurrent.py
clitify/spdislike.py
clitify/splike.py
clitify/spotipytest.py
clitify/spq.py
clitify/spseek.py
clitify-0.1.9.dist-info/entry_points.txt
clitify-0.1.9.dist-info/LICENSE
clitify-0.1.9.dist-info/WHEEL
clitify-0.1.9.dist-info/METADATA
clitify-0.1.9.dist-info/RECORD
